allmdev/__init__.py
allmdev/agentapi.py
allmdev/agentchat.py
allmdev/api.py
allmdev/azureagentapi.py
allmdev/azureagentchat.py
allmdev/azurecli.py
allmdev/backend-old (2).py
allmdev/backend.py
allmdev/chat_history.py
allmdev/cli-old.py
allmdev/cli.py
allmdev/email_test.py
allmdev/instruct-old.py
allmdev/instruct.py
allmdev/newagent.py
allmdev/serve.py
allmdev/updateagent.py
allmdev/vertexagentapi.py
allmdev/vertexagentchat.py
allmdev/vertexcli.py
allmdev-1.5.5.dist-info/METADATA
allmdev-1.5.5.dist-info/WHEEL
allmdev-1.5.5.dist-info/entry_points.txt
allmdev-1.5.5.dist-info/top_level.txt
allmdev-1.5.5.dist-info/RECORD
