Metadata-Version: 2.1
Name: allmdev
Version: 1.5.5
Summary: A simple and efficient python library for fast inference of GGUF Large Language Models.
Author: All Advance AI
Author-email: allmdev@allaai.com
Maintainer: All Advance AI
Maintainer-email: allmdev@allaai.com
Keywords: GGUF,GGUF Large Language Model,GGUF Large Language Models,GGUF Large Language Modeling,GGUF Large Language Modeling Library
Requires-Dist: Flask
Requires-Dist: flask-socketio
Requires-Dist: flask-cors
Requires-Dist: click
Requires-Dist: llama-index
Requires-Dist: llama-cpp-python
Requires-Dist: aiohttp
Requires-Dist: llama-index-llms-llama-cpp
Requires-Dist: huggingface-hub
Requires-Dist: langchain ==0.0.267
Requires-Dist: chromadb ==0.3.26
Requires-Dist: pdfminer.six
Requires-Dist: pydantic ==1.10.13
Requires-Dist: sentence-transformers
Requires-Dist: vertexai
Requires-Dist: google-cloud-aiplatform
Requires-Dist: openai
Requires-Dist: python-multipart
Requires-Dist: pyjwt
Requires-Dist: python-dotenv
Requires-Dist: cryptography
Requires-Dist: easyocr
